{"model":{"models":[{"property":"minecraft:custom_model_data","on_true":{"models":[{"model":"polyfactory:sgui/elements/generic_bar_background_offset_-54","type":"minecraft:model"},{"property":"minecraft:custom_model_data","scale":15.0,"entries":[{"threshold":1.0,"model":{"model":"polyfactory:sgui/elements/gen/generic_bar_1_offset_-54","tints":[{"default":16777215,"type":"minecraft:custom_model_data"}],"type":"minecraft:model"}},{"threshold":2.0,"model":{"model":"polyfactory:sgui/elements/gen/generic_bar_2_offset_-54","tints":[{"default":16777215,"type":"minecraft:custom_model_data"}],"type":"minecraft:model"}},{"threshold":3.0,"model":{"model":"polyfactory:sgui/elements/gen/generic_bar_3_offset_-54","tints":[{"default":16777215,"type":"minecraft:custom_model_data"}],"type":"minecraft:model"}},{"threshold":4.0,"model":{"model":"polyfactory:sgui/elements/gen/generic_bar_4_offset_-54","tints":[{"default":16777215,"type":"minecraft:custom_model_data"}],"type":"minecraft:model"}},{"threshold":5.0,"model":{"model":"polyfactory:sgui/elements/gen/generic_bar_5_offset_-54","tints":[{"default":16777215,"type":"minecraft:custom_model_data"}],"type":"minecraft:model"}},{"threshold":6.0,"model":{"model":"polyfactory:sgui/elements/gen/generic_bar_6_offset_-54","tints":[{"default":16777215,"type":"minecraft:custom_model_data"}],"type":"minecraft:model"}},{"threshold":7.0,"model":{"model":"polyfactory:sgui/elements/gen/generic_bar_7_offset_-54","tints":[{"default":16777215,"type":"minecraft:custom_model_data"}],"type":"minecraft:model"}},{"threshold":8.0,"model":{"model":"polyfactory:sgui/elements/gen/generic_bar_8_offset_-54","tints":[{"default":16777215,"type":"minecraft:custom_model_data"}],"type":"minecraft:model"}},{"threshold":9.0,"model":{"model":"polyfactory:sgui/elements/gen/generic_bar_9_offset_-54","tints":[{"default":16777215,"type":"minecraft:custom_model_data"}],"type":"minecraft:model"}},{"threshold":10.0,"model":{"model":"polyfactory:sgui/elements/gen/generic_bar_10_offset_-54","tints":[{"default":16777215,"type":"minecraft:custom_model_data"}],"type":"minecraft:model"}},{"threshold":11.0,"model":{"model":"polyfactory:sgui/elements/gen/generic_bar_11_offset_-54","tints":[{"default":16777215,"type":"minecraft:custom_model_data"}],"type":"minecraft:model"}},{"threshold":12.0,"model":{"model":"polyfactory:sgui/elements/gen/generic_bar_12_offset_-54","tints":[{"default":16777215,"type":"minecraft:custom_model_data"}],"type":"minecraft:model"}},{"threshold":13.0,"model":{"model":"polyfactory:sgui/elements/gen/generic_bar_13_offset_-54","tints":[{"default":16777215,"type":"minecraft:custom_model_data"}],"type":"minecraft:model"}},{"threshold":14.0,"model":{"model":"polyfactory:sgui/elements/gen/generic_bar_14_offset_-54","tints":[{"default":16777215,"type":"minecraft:custom_model_data"}],"type":"minecraft:model"}}],"fallback":{"type":"minecraft:empty"},"type":"minecraft:range_dispatch"}],"type":"minecraft:composite"},"on_false":{"type":"minecraft:empty"},"type":"minecraft:condition"},{"index":1,"property":"minecraft:custom_model_data","on_true":{"models":[{"model":"polyfactory:sgui/elements/generic_bar_background_offset_-36","type":"minecraft:model"},{"index":1,"property":"minecraft:custom_model_data","scale":15.0,"entries":[{"threshold":1.0,"model":{"model":"polyfactory:sgui/elements/gen/generic_bar_1_offset_-36","tints":[{"index":1,"default":16777215,"type":"minecraft:custom_model_data"}],"type":"minecraft:model"}},{"threshold":2.0,"model":{"model":"polyfactory:sgui/elements/gen/generic_bar_2_offset_-36","tints":[{"index":1,"default":16777215,"type":"minecraft:custom_model_data"}],"type":"minecraft:model"}},{"threshold":3.0,"model":{"model":"polyfactory:sgui/elements/gen/generic_bar_3_offset_-36","tints":[{"index":1,"default":16777215,"type":"minecraft:custom_model_data"}],"type":"minecraft:model"}},{"threshold":4.0,"model":{"model":"polyfactory:sgui/elements/gen/generic_bar_4_offset_-36","tints":[{"index":1,"default":16777215,"type":"minecraft:custom_model_data"}],"type":"minecraft:model"}},{"threshold":5.0,"model":{"model":"polyfactory:sgui/elements/gen/generic_bar_5_offset_-36","tints":[{"index":1,"default":16777215,"type":"minecraft:custom_model_data"}],"type":"minecraft:model"}},{"threshold":6.0,"model":{"model":"polyfactory:sgui/elements/gen/generic_bar_6_offset_-36","tints":[{"index":1,"default":16777215,"type":"minecraft:custom_model_data"}],"type":"minecraft:model"}},{"threshold":7.0,"model":{"model":"polyfactory:sgui/elements/gen/generic_bar_7_offset_-36","tints":[{"index":1,"default":16777215,"type":"minecraft:custom_model_data"}],"type":"minecraft:model"}},{"threshold":8.0,"model":{"model":"polyfactory:sgui/elements/gen/generic_bar_8_offset_-36","tints":[{"index":1,"default":16777215,"type":"minecraft:custom_model_data"}],"type":"minecraft:model"}},{"threshold":9.0,"model":{"model":"polyfactory:sgui/elements/gen/generic_bar_9_offset_-36","tints":[{"index":1,"default":16777215,"type":"minecraft:custom_model_data"}],"type":"minecraft:model"}},{"threshold":10.0,"model":{"model":"polyfactory:sgui/elements/gen/generic_bar_10_offset_-36","tints":[{"index":1,"default":16777215,"type":"minecraft:custom_model_data"}],"type":"minecraft:model"}},{"threshold":11.0,"model":{"model":"polyfactory:sgui/elements/gen/generic_bar_11_offset_-36","tints":[{"index":1,"default":16777215,"type":"minecraft:custom_model_data"}],"type":"minecraft:model"}},{"threshold":12.0,"model":{"model":"polyfactory:sgui/elements/gen/generic_bar_12_offset_-36","tints":[{"index":1,"default":16777215,"type":"minecraft:custom_model_data"}],"type":"minecraft:model"}},{"threshold":13.0,"model":{"model":"polyfactory:sgui/elements/gen/generic_bar_13_offset_-36","tints":[{"index":1,"default":16777215,"type":"minecraft:custom_model_data"}],"type":"minecraft:model"}},{"threshold":14.0,"model":{"model":"polyfactory:sgui/elements/gen/generic_bar_14_offset_-36","tints":[{"index":1,"default":16777215,"type":"minecraft:custom_model_data"}],"type":"minecraft:model"}}],"fallback":{"type":"minecraft:empty"},"type":"minecraft:range_dispatch"}],"type":"minecraft:composite"},"on_false":{"type":"minecraft:empty"},"type":"minecraft:condition"},{"index":2,"property":"minecraft:custom_model_data","on_true":{"models":[{"model":"polyfactory:sgui/elements/generic_bar_background_offset_-18","type":"minecraft:model"},{"index":2,"property":"minecraft:custom_model_data","scale":15.0,"entries":[{"threshold":1.0,"model":{"model":"polyfactory:sgui/elements/gen/generic_bar_1_offset_-18","tints":[{"index":2,"default":16777215,"type":"minecraft:custom_model_data"}],"type":"minecraft:model"}},{"threshold":2.0,"model":{"model":"polyfactory:sgui/elements/gen/generic_bar_2_offset_-18","tints":[{"index":2,"default":16777215,"type":"minecraft:custom_model_data"}],"type":"minecraft:model"}},{"threshold":3.0,"model":{"model":"polyfactory:sgui/elements/gen/generic_bar_3_offset_-18","tints":[{"index":2,"default":16777215,"type":"minecraft:custom_model_data"}],"type":"minecraft:model"}},{"threshold":4.0,"model":{"model":"polyfactory:sgui/elements/gen/generic_bar_4_offset_-18","tints":[{"index":2,"default":16777215,"type":"minecraft:custom_model_data"}],"type":"minecraft:model"}},{"threshold":5.0,"model":{"model":"polyfactory:sgui/elements/gen/generic_bar_5_offset_-18","tints":[{"index":2,"default":16777215,"type":"minecraft:custom_model_data"}],"type":"minecraft:model"}},{"threshold":6.0,"model":{"model":"polyfactory:sgui/elements/gen/generic_bar_6_offset_-18","tints":[{"index":2,"default":16777215,"type":"minecraft:custom_model_data"}],"type":"minecraft:model"}},{"threshold":7.0,"model":{"model":"polyfactory:sgui/elements/gen/generic_bar_7_offset_-18","tints":[{"index":2,"default":16777215,"type":"minecraft:custom_model_data"}],"type":"minecraft:model"}},{"threshold":8.0,"model":{"model":"polyfactory:sgui/elements/gen/generic_bar_8_offset_-18","tints":[{"index":2,"default":16777215,"type":"minecraft:custom_model_data"}],"type":"minecraft:model"}},{"threshold":9.0,"model":{"model":"polyfactory:sgui/elements/gen/generic_bar_9_offset_-18","tints":[{"index":2,"default":16777215,"type":"minecraft:custom_model_data"}],"type":"minecraft:model"}},{"threshold":10.0,"model":{"model":"polyfactory:sgui/elements/gen/generic_bar_10_offset_-18","tints":[{"index":2,"default":16777215,"type":"minecraft:custom_model_data"}],"type":"minecraft:model"}},{"threshold":11.0,"model":{"model":"polyfactory:sgui/elements/gen/generic_bar_11_offset_-18","tints":[{"index":2,"default":16777215,"type":"minecraft:custom_model_data"}],"type":"minecraft:model"}},{"threshold":12.0,"model":{"model":"polyfactory:sgui/elements/gen/generic_bar_12_offset_-18","tints":[{"index":2,"default":16777215,"type":"minecraft:custom_model_data"}],"type":"minecraft:model"}},{"threshold":13.0,"model":{"model":"polyfactory:sgui/elements/gen/generic_bar_13_offset_-18","tints":[{"index":2,"default":16777215,"type":"minecraft:custom_model_data"}],"type":"minecraft:model"}},{"threshold":14.0,"model":{"model":"polyfactory:sgui/elements/gen/generic_bar_14_offset_-18","tints":[{"index":2,"default":16777215,"type":"minecraft:custom_model_data"}],"type":"minecraft:model"}}],"fallback":{"type":"minecraft:empty"},"type":"minecraft:range_dispatch"}],"type":"minecraft:composite"},"on_false":{"type":"minecraft:empty"},"type":"minecraft:condition"},{"index":3,"property":"minecraft:custom_model_data","on_true":{"model":"polyfactory:sgui/elements/empty","type":"minecraft:model"},"on_false":{"type":"minecraft:empty"},"type":"minecraft:condition"}],"type":"minecraft:composite"},"hand_animation_on_swap":false,"oversized_in_gui":true}